call_recorder_api/__init__.py
call_recorder_api/api_client.py
call_recorder_api/configuration.py
call_recorder_api/rest.py
call_recorder_api/api/__init__.py
call_recorder_api/api/default_api.py
call_recorder_api/models/__init__.py
call_recorder_api/models/app.py
call_recorder_api/models/buy_credits_request.py
call_recorder_api/models/buy_credits_response.py
call_recorder_api/models/clone_file_request.py
call_recorder_api/models/clone_file_response.py
call_recorder_api/models/create_file_data.py
call_recorder_api/models/create_file_request.py
call_recorder_api/models/create_file_response.py
call_recorder_api/models/create_folder_request.py
call_recorder_api/models/create_folder_response.py
call_recorder_api/models/delete_files_request.py
call_recorder_api/models/delete_files_response.py
call_recorder_api/models/delete_folder_request.py
call_recorder_api/models/delete_folder_response.py
call_recorder_api/models/delete_meta_files_request.py
call_recorder_api/models/delete_meta_files_response.py
call_recorder_api/models/device_type.py
call_recorder_api/models/files_permission.py
call_recorder_api/models/get_files_request.py
call_recorder_api/models/get_files_response.py
call_recorder_api/models/get_files_response_files.py
call_recorder_api/models/get_folders_request.py
call_recorder_api/models/get_folders_response.py
call_recorder_api/models/get_folders_response_folders.py
call_recorder_api/models/get_languages_request.py
call_recorder_api/models/get_languages_response.py
call_recorder_api/models/get_languages_response_languages.py
call_recorder_api/models/get_messages_request.py
call_recorder_api/models/get_messages_response.py
call_recorder_api/models/get_messages_response_msgs.py
call_recorder_api/models/get_meta_files_request.py
call_recorder_api/models/get_meta_files_response.py
call_recorder_api/models/get_meta_files_response_meta_files.py
call_recorder_api/models/get_phones_request.py
call_recorder_api-1.0.1.dist-info/DESCRIPTION.rst
call_recorder_api-1.0.1.dist-info/METADATA
call_recorder_api-1.0.1.dist-info/RECORD
call_recorder_api-1.0.1.dist-info/WHEEL
call_recorder_api-1.0.1.dist-info/metadata.json
call_recorder_api-1.0.1.dist-info/top_level.txt
